amazon_ads_api/__init__.py
amazon_ads_api/base.py
amazon_ads_api/client.py
amazon_ads_api/core/__init__.py
amazon_ads_api/core/accounts/__init__.py
amazon_ads_api/core/accounts/advertising_accounts.py
amazon_ads_api/core/accounts/billing.py
amazon_ads_api/core/accounts/budgets.py
amazon_ads_api/core/accounts/portfolios.py
amazon_ads_api/core/accounts/profiles.py
amazon_ads_api/core/accounts/test_accounts.py
amazon_ads_api/core/audiences/__init__.py
amazon_ads_api/core/audiences/audiences_discovery.py
amazon_ads_api/core/dsp/__init__.py
amazon_ads_api/core/dsp/advertisers.py
amazon_ads_api/core/dsp/audiences.py
amazon_ads_api/core/dsp/campaigns.py
amazon_ads_api/core/dsp/conversions.py
amazon_ads_api/core/dsp/measurement.py
amazon_ads_api/core/dsp/target_kpi.py
amazon_ads_api/core/eligibility/__init__.py
amazon_ads_api/core/eligibility/eligibility.py
amazon_ads_api/core/exports/__init__.py
amazon_ads_api/core/exports/exports.py
amazon_ads_api/core/locations/__init__.py
amazon_ads_api/core/locations/locations.py
amazon_ads_api/core/products/__init__.py
amazon_ads_api/core/products/product_selector.py
amazon_ads_api/core/sb/__init__.py
amazon_ads_api/core/sb/ads.py
amazon_ads_api/core/sb/brand_video.py
amazon_ads_api/core/sb/campaigns.py
amazon_ads_api/core/sb/creatives.py
amazon_ads_api/core/sb/forecasts.py
amazon_ads_api/core/sb/keywords.py
amazon_ads_api/core/sb/legacy_migration.py
amazon_ads_api/core/sb/media.py
amazon_ads_api/core/sb/moderation.py
amazon_ads_api/core/sb/optimization.py
amazon_ads_api/core/sb/reports_v2.py
amazon_ads_api/core/sb/stores.py
amazon_ads_api/core/sb/targeting.py
amazon_ads_api/core/sb/themes.py
amazon_ads_api/core/sd/__init__.py
amazon_ads_api/core/sd/audiences.py
amazon_ads_api/core/sd/brand_safety.py
amazon_ads_api/core/sd/campaigns.py
amazon_ads_api/core/sd/creatives.py
amazon_ads_api/core/sd/locations.py
amazon_ads_api/core/sd/moderation.py
amazon_ads_api/core/sd/optimization.py
amazon_ads_api/core/sd/reports.py
amazon_ads_api-1.0.0.dist-info/METADATA
amazon_ads_api-1.0.0.dist-info/WHEEL
amazon_ads_api-1.0.0.dist-info/licenses/LICENSE
amazon_ads_api-1.0.0.dist-info/RECORD
