Metadata-Version: 2.4
Name: amazon-ads-api
Version: 1.0.0
Summary: Python SDK for Amazon Ads API - 100% API Coverage (101 classes)
Project-URL: Homepage, https://github.com/vanling1111/amazon-ads-api-python-sdk
Project-URL: Documentation, https://github.com/vanling1111/amazon-ads-api-python-sdk#readme
Project-URL: Repository, https://github.com/vanling1111/amazon-ads-api-python-sdk.git
Project-URL: Issues, https://github.com/vanling1111/amazon-ads-api-python-sdk/issues
Project-URL: Changelog, https://github.com/vanling1111/amazon-ads-api-python-sdk/blob/master/CHANGELOG.md
Author-email: vanling1111 <vanling1111@gmail.com>
Maintainer-email: vanling1111 <vanling1111@gmail.com>
License: MIT
License-File: LICENSE
Keywords: ads,advertising,amazon,amazon-ads,amazon-marketing-cloud,amc,api,dsp,sdk,sponsored-brands,sponsored-display,sponsored-products
Classifier: Development Status :: 5 - Production/Stable
Classifier: Intended Audience :: Developers
Classifier: License :: OSI Approved :: MIT License
Classifier: Operating System :: OS Independent
Classifier: Programming Language :: Python :: 3
Classifier: Programming Language :: Python :: 3.11
Classifier: Programming Language :: Python :: 3.12
Classifier: Topic :: Internet :: WWW/HTTP :: Dynamic Content
Classifier: Topic :: Software Development :: Libraries :: Python Modules
Requires-Python: >=3.11
Requires-Dist: httpx[http2]>=0.27.0
Requires-Dist: loguru>=0.7.0
Provides-Extra: dev
Requires-Dist: black>=23.0.0; extra == 'dev'
Requires-Dist: mypy>=1.0.0; extra == 'dev'
Requires-Dist: pytest-asyncio>=0.21.0; extra == 'dev'
Requires-Dist: pytest-cov>=4.0.0; extra == 'dev'
Requires-Dist: pytest-mock>=3.10.0; extra == 'dev'
Requires-Dist: pytest>=7.0.0; extra == 'dev'
Requires-Dist: ruff>=0.1.0; extra == 'dev'
Provides-Extra: test
Requires-Dist: pytest-asyncio>=0.21.0; extra == 'test'
Requires-Dist: pytest-cov>=4.0.0; extra == 'test'
Requires-Dist: pytest-mock>=3.10.0; extra == 'test'
Requires-Dist: pytest>=7.0.0; extra == 'test'
